Workbook

Sheet FSM Forecast
C2: ="Financial Statement Model for "&D5 -> Financial Statement Model for Micron
C3: $ in thousands except per share
C5: Company name | D5: Micron
C6: Ticker | D6: MU
C7: Circ break 1=off, 0=on | D7: 1
C8: Latest closing share price date | D8: 45937
C9: Latest closing share price | D9: 185.69
C10: Latest fiscal year end date | D10: 45897
C11: Shares outstanding (millions) | D11: 1122.466
C12: Active Case | D12: Base Case
B14: x | C14: INCOME STATEMENT
C15: Fiscal year | D15: =E15-1 -> 2023 | E15: =F15-1 -> 2024 | F15: 2025 | G15: 2026 | H15: =G15+1 -> 2027 | I15: =H15+1 -> 2028 | J15: =I15+1 -> 2029 | K15: =J15+1 -> 2030
C16: Fiscal year end date | D16: =DATE(2024,8,29)-364 -> 45169 | E16: =DATE(2025,8,28)-364 -> 45533 | F16: =D10 -> 45897 | G16: =DATE(2025,8,28)+364 -> 46261 | H16: =DATE(2026,8,27)+364 -> 46625 | I16: =DATE(2027,8,26)+371 -> 46996 | J16: =DATE(2028,8,31)+364 -> 47360 | K16: =DATE(2029,8,30)+364 -> 47724 | M16: Comment
C18: Revenue | D18: 15540 | E18: 25111 | F18: 37378 | G18: =F18*(1+G39) -> 54518.178 | H18: =G18*(1+H39) -> 67519.534 | I18: =H18*(1+I39) -> 74513.923 | J18: =I18*(1+J39) -> 78893.684 | K18: =J18*(1+K39) -> 83389.786 | M18: Prior year * (1+g)
C19: Cost of sales (enter as -) | D19: -16956 | E19: -19498 | F19: -22505 | G19: =G20-G18 -> -26375.894 | H19: =H20-H18 -> -36717.123 | I19: =I20-I18 -> -44991.506 | J19: =J20-J18 -> -52369.628 | K19: =K20-K18 -> -60357.527 | M19: Plug = Revenue - Gross Profit
C20: Gross Profit | D20: =SUM(D18:D19) -> -1416 | E20: =SUM(E18:E19) -> 5613 | F20: =SUM(F18:F19) -> 14873 | G20: =G18*G40 -> 28142.283 | H20: =H18*H40 -> 30802.411 | I20: =I18*I40 -> 29522.416 | J20: =J18*J40 -> 26524.057 | K20: =K18*K40 -> 23032.259 | M20: Revenue x Gross Profit Margin forecast
C21: Research & development (enter as -) | D21: -3114 | E21: -3430 | F21: -3798 | G21: =F21*(1+G41) -> -4132.224 | H21: =G21*(1+H41) -> -4514.0415 | I21: =H21*(1+I41) -> -4929.3333 | J21: =I21*(1+J41) -> -5382.832 | K21: =J21*(1+K41) -> -5878.0525 | M21: Revenue x R&D % of sales forecast
C22: Selling, general & administrative (enter as -) | D22: -920 | E22: -1129 | F22: -1205 | G22: =F22*(1+G42) -> -1235.125 | H22: =G22*(1+H42) -> -1266.0031 | I22: =H22*(1+I42) -> -1297.6532 | J22: =I22*(1+J42) -> -1330.0945 | K22: =J22*(1+K42) -> -1363.3469 | M22: Revenue x SG&A % of sales forecast
C23: Restructuring & asset impairments | D23: -171 | E23: -1 | F23: -39 | G23: 0 | H23: 0 | I23: 0 | J23: 0 | K23: 0
C24: Other operating income (expense), net | D24: -124 | E24: 251 | F24: -61 | G24: 0 | H24: 0 | I24: 0 | J24: 0 | K24: 0
C25: Operating profit (EBIT) | D25: =SUM(D20:D24) -> -5745 | E25: =SUM(E20:E24) -> 1304 | F25: =SUM(F20:F24) -> 9770 | G25: =SUM(G20:G22) -> 22774.934 | H25: =SUM(H20:H22) -> 25022.367 | I25: =SUM(I20:I22) -> 23295.43 | J25: =SUM(J20:J22) -> 19811.13 | K25: =SUM(K20:K22) -> 15790.859 | M25: Gross Profit - R&D - SG&A
C26: Interest income | D26: 468 | E26: 529 | F26: 496 | G26: =G169 -> 663.77892 | H26: =H169 -> 850.11784 | I26: =I169 -> 1434.4651 | J26: =J169 -> 2070.8525 | K26: =K169 -> 2661.7211 | M26: Reference from interest on cash schedule
C27: Interest expense (enter as -) | D27: -388 | E27: -562 | F27: -477 | G27: =-G152 -> -430.1425 | H27: =-H152 -> -417.3925 | I27: =-I152 -> -417.3925 | J27: =-J152 -> -417.3925 | K27: =-K152 -> -417.3925 | M27: Reference from interest expense schedule
C28: Other expense, net (enter as -) | D28: 7 | E28: -31 | F28: -135 | G28: =F28 -> -135 | H28: =G28 -> -135 | I28: =H28 -> -135 | J28: =I28 -> -135 | K28: =J28 -> -135 | M28: Straight-line
C29: Pretax profit | D29: =SUM(D25:D28) -> -5658 | E29: =SUM(E25:E28) -> 1240 | F29: =SUM(F25:F28) -> 9654 | G29: =SUM(G25:G28) -> 22873.571 | H29: =SUM(H25:H28) -> 25320.092 | I29: =SUM(I25:I28) -> 24177.502 | J29: =SUM(J25:J28) -> 21329.59 | K29: =SUM(K25:K28) -> 17900.188 | M29: EBIT + interest income less interest expense less other expense
C30: Taxes (enter expense as -) | D30: -177 | E30: -451 | F30: -1124 | G30: =-G29*G43 -> -3774.1392 | H30: =-H29*H43 -> -4177.8152 | I30: =-I29*I43 -> -3989.2879 | J30: =-J29*J43 -> -3519.3824 | K30: =-K29*K43 -> -2953.531 | M30: Pre-tax Profit x Tax Rate forecast
C31: Net income | D31: =SUM(D29:D30) -> -5835 | E31: =SUM(E29:E30) -> 789 | F31: =SUM(F29:F30) -> 8530 | G31: =SUM(G29:G30) -> 19099.432 | H31: =SUM(H29:H30) -> 21142.277 | I31: =SUM(I29:I30) -> 20188.214 | J31: =SUM(J29:J30) -> 17810.208 | K31: =SUM(K29:K30) -> 14946.657 | M31: Pre-tax Profit less taxes
C33: Depreciation & amortization | D33: 7756 | E33: 7780 | F33: 8352 | G33: =G116 -> 16187.277 | H33: =H116 -> 15738.472 | I33: =I116 -> 16343.677 | J33: =J116 -> 17372.288 | K33: =K116 -> 18170.91 | M33: Reference from D&A schedule
C34: EBITDA | D34: =D33+D25 -> 2011 | E34: =E33+E25 -> 9084 | F34: =F33+F25 -> 18122 | G34: =G33+G25 -> 38962.212 | H34: =H33+H25 -> 40760.839 | I34: =I33+I25 -> 39639.107 | J34: =J33+J25 -> 37183.418 | K34: =K33+K25 -> 33961.769
C35: Stock based compensation | D35: 596 | E35: 833 | F35: 972 | G35: =F35*(1+G39) -> 1417.7235 | H35: =G35*(1+H39) -> 1755.8186 | I35: =H35*(1+I39) -> 1937.7049 | J35: =I35*(1+J39) -> 2051.5988 | K35: =J35*(1+K39) -> 2168.5182 | M35: Assumption grow in line with revenue
C36: Adjusted EBITDA | D36: =SUM(D34:D35) -> 2607 | E36: =SUM(E34:E35) -> 9917 | F36: =SUM(F34:F35) -> 19094 | G36: =SUM(G34:G35) -> 40379.935 | H36: =SUM(H34:H35) -> 42516.657 | I36: =SUM(I34:I35) -> 41576.812 | J36: =SUM(J34:J35) -> 39235.017 | K36: =SUM(K34:K35) -> 36130.287 | M36: EBITDA + Stock-based compensation
C38: Growth rates & margins
C39: Revenue growth | E39: =E18/D18-1 -> 0.61589447 | F39: =F18/E18-1 -> 0.48851101 | G39: =G219 -> 0.45856327 | H39: =H219 -> 0.23847745 | I39: =I219 -> 0.10359059 | J39: =J219 -> 0.058777765 | K39: =K219 -> 0.056989372 | M39: Imported from scenario analysis
C40: Gross profit margin | D40: =D20/D18 -> -0.091119691 | E40: =E20/E18 -> 0.22352754 | F40: =F20/F18 -> 0.39790786 | G40: =G220 -> 0.5162 | H40: =H220 -> 0.4562 | I40: =I220 -> 0.3962 | J40: =J220 -> 0.3362 | K40: =K220 -> 0.2762 | M40: Imported from scenario analysis
C41: R&D % of sales | D41: =-(D21/D18) -> 0.2003861 | E41: =-(E21/E18) -> 0.13659352 | F41: =-(F21/F18) -> 0.10161057 | G41: =G221 -> 0.088 | H41: =H221 -> 0.0924 | I41: =I221 -> 0.092 | J41: =J221 -> 0.092 | K41: =K221 -> 0.092 | M41: Imported from scenario analysis
C42: SG&A % of sales | D42: =-(D22/D18) -> 0.059202059 | E42: =-(E22/E18) -> 0.044960376 | F42: =-(F22/F18) -> 0.032238215 | G42: =G222 -> 0.025 | H42: =H222 -> 0.025 | I42: =I222 -> 0.025 | J42: =J222 -> 0.025 | K42: =K222 -> 0.025 | M42: Imported from scenario analysis
C43: Tax rate | D43: =D30/D29 -> 0.031283139 | E43: =-E30/E29 -> 0.36370968 | F43: =-F30/F29 -> 0.11642842 | G43: 0.165 | H43: 0.165 | I43: 0.165 | J43: 0.165 | K43: 0.165 | M43: TS Assumption
B45: x | C45: BALANCE SHEET
C46: Fiscal year | E46: =F46-1 -> 2024 | F46: 2025 | G46: 2026 | H46: =G46+1 -> 2027 | I46: =H46+1 -> 2028 | J46: =I46+1 -> 2029 | K46: =J46+1 -> 2030
C47: Fiscal year end date | E47: =DATE(2025,8,28)-364 -> 45533 | F47: =D10 -> 45897 | G47: =DATE(2025,8,28)+364 -> 46261 | H47: =DATE(2026,8,27)+364 -> 46625 | I47: =DATE(2027,8,26)+371 -> 46996 | J47: =DATE(2028,8,31)+364 -> 47360 | K47: =DATE(2029,8,30)+364 -> 47724
C48: Cash & equivalents, ST and LT marketable securities | E48: =7041+1065+1046 -> 9152 | F48: =9642+665+1629 -> 11936 | G48: =F48+G100 -> 21252.946 | H48: =G48+H100 -> 35861.626 | I48: =H48+I100 -> 51771.313 | J48: =I48+J100 -> 66543.028 | K48: =J48+K100 -> 79104.181 | M48: Reference from 'net change in cash' line on the cash flow statement
C49: Accounts receivable | E49: 6615 | F49: 9265 | G49: =F49*(1+G39) -> 13513.589 | H49: =G49*(1+H39) -> 16736.275 | I49: =H49*(1+I39) -> 18469.996 | J49: =I49*(1+J39) -> 19555.621 | K49: =J49*(1+K39) -> 20670.083 | M49: Grow in-line with revenue growth
C50: Inventories | E50: 8875 | F50: 8355 | G50: =(F50)*(G19/F19) -> 9792.0728 | H50: =(G50)*(H19/G19) -> 13631.262 | I50: =(H50)*(I19/H19) -> 16703.134 | J50: =(I50)*(J19/I19) -> 19442.268 | K50: =(J50)*(K19/J19) -> 22407.782 | M50: Grow in-line with cost of sales growth
C51: Other current assets | E51: 776 | F51: 914 | G51: =F51*(1+G39) -> 1333.1268 | H51: =G51*(1+H39) -> 1651.0475 | I51: =H51*(1+I39) -> 1822.0805 | J51: =I51*(1+J39) -> 1929.1783 | K51: =J51*(1+K39) -> 2039.121 | M51: Grow in-line with revenue growth
C52: Property, plant & equipment | E52: 39749 | F52: 46590 | G52: =G109 -> 51958.5 | H52: =H109 -> 56435.868 | I52: =I109 -> 60372.332 | J52: =J109 -> 63849.8 | K52: =K109 -> 66794.28 | M52: Reference from PP&E schedule
C53: Operating lease right-of-use assets | E53: 645 | F53: 736 | G53: =$F$53 -> 736 | H53: =G53 -> 736 | I53: =H53 -> 736 | J53: =I53 -> 736 | K53: =J53 -> 736 | M53: Straight line
C54: Intangible assets | E54: 416 | F54: 453 | G54: 453 | H54: 453 | I54: 453 | J54: 453 | K54: 453 | M54: Straight line
C55: Deferred tax assets | E55: 520 | F55: 616 | G55: 616 | H55: 616 | I55: 616 | J55: 616 | K55: 616 | M55: Straight line
C56: Goodwill | E56: 1150 | F56: 1150 | G56: 1150 | H56: 1150 | I56: 1150 | J56: 1150 | K56: 1150 | M56: Straight line
C57: Other non current assets | E57: 1518 | F57: 2783 | G57: =F57*(1+G39) -> 4059.1816 | H57: =G57*(1+H39) -> 5027.2049 | I57: =H57*(1+I39) -> 5547.976 | J57: =I57*(1+J39) -> 5874.0736 | K57: =J57*(1+K39) -> 6208.8334 | M57: Grow in-line with revenue growth
C58: Total assets | E58: =SUM(E48:E57) -> 69416 | F58: =SUM(F48:F57) -> 82798 | G58: =SUM(G48:G57) -> 104864.42 | H58: =SUM(H48:H57) -> 132298.28 | I58: =SUM(I48:I57) -> 157641.83 | J58: =SUM(J48:J57) -> 180148.97 | K58: =SUM(K48:K57) -> 200179.28
C60: Accounts payable | E60: 7299 | F60: 9649 | G60: =F60*(G19/F19) -> 11308.643 | H60: =G60*(H19/G19) -> 15742.436 | I60: =H60*(I19/H19) -> 19290.071 | J60: =I60*(J19/I19) -> 22453.434 | K60: =J60*(K19/J19) -> 25878.239 | M60: Grow in-line with cost of sales growth
C61: Other current liabilities | E61: 1518 | F61: 1245 | G61: =F61*(1+G39) -> 1815.9113 | H61: =G61*(1+H39) -> 2248.9652 | I61: =H61*(1+I39) -> 2481.9368 | J61: =I61*(1+J39) -> 2627.8195 | K61: =J61*(1+K39) -> 2777.5773 | M61: Grow in-line with revenue growth
C62: Commercial paper / revolver | E62: 431 | F62: 560 | G62: =G145 -> 50 | H62: =H145 -> 50 | I62: =I145 -> 50 | J62: =J145 -> 50 | K62: =K145 -> 50 | M62: Reference from revolver schedule
C63: Long term debt (includes current portion) | E63: 12966 | F63: 14017 | G63: 14017 | H63: 14017 | I63: 14017 | J63: 14017 | K63: 14017 | M63: TS assumption: straight-line
C64: Noncurrent operating lease liabilities | E64: 610 | F64: 701 | G64: 701 | H64: 701 | I64: 701 | J64: 701 | K64: 701 | M64: Straight line
C65: Noncurrent unearned government incentives | E65: 550 | F65: 1018 | G65: 1018 | H65: 1018 | I65: 1018 | J65: 1018 | K65: 1018 | M65: Straight line
C66: Other non current liabilities | E66: 911 | F66: 1443 | G66: =F66*(1+G39) -> 2104.7068 | H66: =G66*(1+H39) -> 2606.6319 | I66: =H66*(1+I39) -> 2876.6545 | J66: =I66*(1+J39) -> 3045.7378 | K66: =J66*(1+K39) -> 3219.3125 | M66: Grow in-line with revenue growth
C67: Total liabilities | E67: =SUM(E60:E66) -> 24285 | F67: =SUM(F60:F66) -> 28633 | G67: =SUM(G60:G66) -> 31015.261 | H67: =SUM(H60:H66) -> 36384.033 | I67: =SUM(I60:I66) -> 40434.662 | J67: =SUM(J60:J66) -> 43912.991 | K67: =SUM(K60:K66) -> 47661.129
C69: Common stock | E69: 125 | F69: 127 | G69: =F69+G35 -> 1544.7235 | H69: =G69+H35 -> 3300.5421 | I69: =H69+I35 -> 5238.247 | J69: =I69+J35 -> 7289.8458 | K69: =J69+K35 -> 9458.364 | M69: Increase by stock-based compensation forecasted in the I/S section
C70: Additional Capital | E70: 12115 | F70: 13339 | G70: 13339 | H70: 13339 | I70: 13339 | J70: 13339 | K70: 13339
C71: Retained earnings | E71: 40877 | F71: 48583 | G71: =G129 -> 66849.432 | H71: =H129 -> 87158.709 | I71: =I129 -> 106513.92 | J71: =J129 -> 123491.13 | K71: =K129 -> 137604.79 | M71: Reference from Retained Earnings schedule
C72: Treasury Stock | E72: -7852 | F72: -7852 | G72: -7852 | H72: -7852 | I72: -7852 | J72: -7852 | K72: -7852
C73: Other comprehensive income | E73: -134 | F73: -32 | G73: =F73 -> -32 | H73: =G73 -> -32 | I73: =H73 -> -32 | J73: =I73 -> -32 | K73: =J73 -> -32 | M73: TS assumption: straight-line
C74: Total equity | E74: =SUM(E69:E73) -> 45131 | F74: =SUM(F69:F73) -> 54165 | G74: =SUM(G69:G73) -> 73849.155 | H74: =SUM(H69:H73) -> 95914.251 | I74: =SUM(I69:I73) -> 117207.17 | J74: =SUM(J69:J73) -> 136235.98 | K74: =SUM(K69:K73) -> 152518.15
C76: Balance check | E76: =E58-E67-E74 -> 0 | F76: =F58-F67-F74 -> 0 | G76: =G58-G67-G74 -> 0 | H76: =H58-H67-H74 -> 2.446468e-07 | I76: =I58-I67-I74 -> 8.2125189e-07 | J76: =J58-J67-J74 -> 1.7114333e-05 | K76: =K58-K67-K74 -> 5.6569232e-05
B78: x | C78: CASH FLOW STATEMENT
C79: Fiscal year | G79: 2026 | H79: =G79+1 -> 2027 | I79: =H79+1 -> 2028 | J79: =I79+1 -> 2029 | K79: =J79+1 -> 2030
C80: Fiscal year end date | G80: =DATE(2025,8,28)+364 -> 46261 | H80: =DATE(2026,8,27)+364 -> 46625 | I80: =DATE(2027,8,26)+371 -> 46996 | J80: =DATE(2028,8,31)+364 -> 47360 | K80: =DATE(2029,8,30)+364 -> 47724
C82: Net income | G82: =G31 -> 19099.432 | H82: =H31 -> 21142.277 | I82: =I31 -> 20188.214 | J82: =J31 -> 17810.208 | K82: =K31 -> 14946.657
C83: Depreciation and amortization | G83: =G33 -> 16187.277 | H83: =H116 -> 15738.472 | I83: =I116 -> 16343.677 | J83: =J116 -> 17372.288 | K83: =K116 -> 18170.91
C84: Stock based compensation | G84: =G35 -> 1417.7235 | H84: =H35 -> 1755.8186 | I84: =I35 -> 1937.7049 | J84: =J35 -> 2051.5988 | K84: =K35 -> 2168.5182
C85: Decreases / (Increases) in working capital assets | G85: =SUM(F49:F51)-SUM(G49:G51) -> -6104.7883 | H85: =SUM(G49:G51)-SUM(H49:H51) -> -7379.7965 | I85: =SUM(H49:H51)-SUM(I49:I51) -> -4976.6254 | J85: =SUM(I49:I51)-SUM(J49:J51) -> -3931.8565 | K85: =SUM(J49:J51)-SUM(K49:K51) -> -4189.9195
C86: Increases / (Decreases) in working capital liabilities | G86: =SUM(G60:G61)-SUM(F60:F61) -> 2230.5541 | H86: =SUM(H60:H61)-SUM(G60:G61) -> 4866.8469 | I86: =SUM(I60:I61)-SUM(H60:H61) -> 3780.6068 | J86: =SUM(J60:J61)-SUM(I60:I61) -> 3309.246 | K86: =SUM(K60:K61)-SUM(J60:J61) -> 3574.563
C87: Other non current assets | G87: =-G121 -> -1357.9589 | H87: =-H121 -> -1060.8626 | I87: =-I121 -> -613.91352 | J87: =-J121 -> -414.85302 | K87: =-K121 -> -418.14955 | M87: Reference additions to 'other non-current assets' from schedule
C88: Other non current liabilities | G88: =G66-F66 -> 661.7068 | H88: =H66-G66 -> 501.92512 | I88: =I66-H66 -> 270.02254 | J88: =J66-I66 -> 169.08332 | K88: =K66-J66 -> 173.57468
C89: Cash from operating activities | G89: =SUM(G82:G88) -> 32133.946 | H89: =SUM(H82:H88) -> 35564.68 | I89: =SUM(I82:I88) -> 36929.687 | J89: =SUM(J82:J88) -> 36365.714 | K89: =SUM(K82:K88) -> 34426.154
C91: Capital expenditures | G91: =-G107 -> -21474 | H91: =-H107 -> -20123 | I91: =-I107 -> -20187 | J91: =-J107 -> -20761 | K91: =-K107 -> -21032
C92: Cash from investing activities | G92: =G91 -> -21474 | H92: =H91 -> -20123 | I92: =I91 -> -20187 | J92: =J91 -> -20761 | K92: =K91 -> -21032
C94: Long term debt | G94: =G63-F63 -> 0 | H94: =H63-G63 -> 0 | I94: =I63-H63 -> 0 | J94: =J63-I63 -> 0 | K94: =K63-J63 -> 0
C95: Revolver | G95: =G62-F62 -> -510 | H95: =H62-G62 -> 0 | I95: =I62-H62 -> 0 | J95: =J62-I62 -> 0 | K95: =K62-J62 -> 0
C96: Share repurchases | G96: =G128 -> -306 | H96: =H128 -> -306 | I96: =I128 -> -306 | J96: =J128 -> -306 | K96: =K128 -> -306
C97: Common dividends | G97: =G127 -> -527 | H97: =H127 -> -527 | I97: =I127 -> -527 | J97: =J127 -> -527 | K97: =K127 -> -527
C98: Cash from financing activities | G98: =SUM(G94:G97) -> -1343 | H98: =SUM(H94:H97) -> -833 | I98: =SUM(I94:I97) -> -833 | J98: =SUM(J94:J97) -> -833 | K98: =SUM(K94:K97) -> -833
C100: Net change in cash during period | G100: =G98+G89+G92 -> 9316.9461 | H100: =H98+H89+H92 -> 14608.68 | I100: =I98+I89+I92 -> 15909.687 | J100: =J98+J89+J92 -> 14771.714 | K100: =K98+K89+K92 -> 12561.154
B102: x | C102: PROPERTY, PLANT & EQUIPMENT
C103: Fiscal year | D103: =E103-1 -> 2023 | E103: =F103-1 -> 2024 | F103: 2025 | G103: 2026 | H103: =G103+1 -> 2027 | I103: =H103+1 -> 2028 | J103: =I103+1 -> 2029 | K103: =J103+1 -> 2030
C104: Fiscal year end date | D104: =DATE(2024,8,29)-364 -> 45169 | E104: =DATE(2025,8,28)-364 -> 45533 | F104: =D10 -> 45897 | G104: =DATE(2025,8,28)+364 -> 46261 | H104: =DATE(2026,8,27)+364 -> 46625 | I104: =DATE(2027,8,26)+371 -> 46996 | J104: =DATE(2028,8,31)+364 -> 47360 | K104: =DATE(2029,8,30)+364 -> 47724
G105: Forecast
C106: Beginning of period | G106: =F109 -> 46590 | H106: =G109 -> 51958.5 | I106: =H109 -> 56435.868 | J106: =I109 -> 60372.332 | K106: =J109 -> 63849.8 | M106: BOP = Previous year EOP
C107: Plus: Capital expenditures | D107: 7680 | E107: 8390 | F107: 15860 | G107: 21474 | H107: 20123 | I107: 20187 | J107: 20761 | K107: 21032 | M107: Morningstar Report Assumption
C108: Less: Depreciation | D108: -7670 | E108: -7700 | F108: -8280 | G108: =-(G107*G111) -> -16105.5 | H108: =-(H107*H111) -> -15645.632 | I108: =-(I107*I111) -> -16250.535 | J108: =-(J107*J111) -> -17283.532 | K108: =-(K107*K111) -> -18087.52 | M108: Capex x 'D&A related to PP&E as a % of capex' ratio (below)
C109: End of period | E109: =E52 -> 39749 | F109: =F52 -> 46590 | G109: =SUM(G106:G108) -> 51958.5 | H109: =SUM(H106:H108) -> 56435.868 | I109: =SUM(I106:I108) -> 60372.332 | J109: =SUM(J106:J108) -> 63849.8 | K109: =SUM(K106:K108) -> 66794.28 | M109: BOP + Capex - Depreciation
L110: Step
C111: D&A related to PP&E as a % of capex | D111: =-(D108/D107) -> 0.99869792 | E111: =-(E108/E107) -> 0.91775924 | F111: =-(F108/F107) -> 0.5220681 | G111: 0.75 | H111: =G111+$L$111 -> 0.7775 | I111: =H111+$L$111 -> 0.805 | J111: =I111+$L$111 -> 0.8325 | K111: =J111+$L$111 -> 0.86 | L111: 0.0275
B113: x | C113: IMPUTING TOTAL DEPRECIATION & AMORTIZATION
C114: D&A not related to PP&E | D114: =D116+D108 -> 86 | E114: =E116+E108 -> 80 | F114: =F116+F108 -> 72 | G114: =G115*G18 -> 81.777267 | H114: =H115*H18 -> 92.839359 | I114: =I115*I18 -> 93.142403 | J114: =J115*J18 -> 88.755395 | K114: =K115*K18 -> 83.389786 | L114: Step
C115: as % of revenue | D115: =D114/D18 -> 0.0055341055 | E115: =E114/E18 -> 0.0031858548 | F115: =F114/F18 -> 0.0019262668 | G115: 0.0015 | H115: =G115-$L$115 -> 0.001375 | I115: =H115-$L$115 -> 0.00125 | J115: =I115-$L$115 -> 0.001125 | K115: =J115-$L$115 -> 0.001 | L115: 0.000125
C116: Depreciation & Amortization - Total | D116: =D33 -> 7756 | E116: =E33 -> 7780 | F116: =F33 -> 8352 | G116: =-(G108-G114) -> 16187.277 | H116: =-(H108-H114) -> 15738.472 | I116: =-(I108-I114) -> 16343.677 | J116: =-(J108-J114) -> 17372.288 | K116: =-(K108-K114) -> 18170.91
C118: OTHER NON-CURRENT ASSETS
...

Sheet Revenue Build
C2: Price / volume build
C3: Fiscal year | E3: 2024 | F3: 2025 | G3: 2026 | H3: =G3+1 -> 2027 | I3: =H3+1 -> 2028 | J3: =I3+1 -> 2029 | K3: =J3+1 -> 2030
C4: Fiscal year end date | E4: =DATE(2025,8,28)-364 -> 45533 | F4: ='FSM Forecast'!D10 -> 45897 | G4: =DATE(2025,8,28)+364 -> 46261 | H4: =DATE(2026,8,27)+364 -> 46625 | I4: =DATE(2027,8,26)+371 -> 46996 | J4: =DATE(2028,8,31)+364 -> 47360 | K4: =DATE(2029,8,30)+364 -> 47724
C5: Revenue by product
C6: Core products
C8: DRAM | E8: 17600 | F8: 28580 | G8: =F8*(1+G22) -> 43135.794 | H8: =G8*(1+H22) -> 54001.701 | I8: =H8*(1+I22) -> 59715.08 | J8: =I8*(1+J22) -> 63309.928 | K8: =J8*(1+K22) -> 67121.186
C9: NAND | E9: 7230 | F9: 8500 | G9: =F9*(1+G23) -> 10949.7 | H9: =G9*(1+H23) -> 12981.964 | I9: =H9*(1+I23) -> 14207.462 | J9: =I9*(1+J23) -> 14957.616 | K9: =J9*(1+K23) -> 15606.776
C10: Total Revenue | E10: =SUM(E8:E9) -> 24830 | F10: =SUM(F8:F9) -> 37080 | G10: =SUM(G8:G9) -> 54085.494 | H10: =SUM(H8:H9) -> 66983.665 | I10: =SUM(I8:I9) -> 73922.542 | J10: =SUM(J8:J9) -> 78267.544 | K10: =SUM(K8:K9) -> 82727.962
C11: % growth | F11: =F10/E10-1 -> 0.49335481 | G11: =G10/F10-1 -> 0.45861634 | H11: =H10/G10-1 -> 0.23847745 | I11: =I10/H10-1 -> 0.10359059 | J11: =J10/I10-1 -> 0.058777765 | K11: =K10/J10-1 -> 0.056989372
C13: Bit Demand Growth
C14: DRAM | G14: 0.17 | H14: 0.17 | I14: 0.14 | J14: 0.14 | K14: 0.14
C15: NAND | G15: 0.14 | H15: 0.14 | I15: 0.14 | J15: 0.12 | K15: 0.11
C17: Average Selling Price Change
C18: DRAM | G18: 0.29 | H18: 0.07 | I18: -0.03 | J18: -0.07 | K18: -0.07
C19: NAND | G19: 0.13 | H19: 0.04 | I19: -0.04 | J19: -0.06 | K19: -0.06
C21: Revenue Growth
C22: DRAM | G22: =(1+G14)*(1+G18)-1 -> 0.5093 | H22: =(1+H14)*(1+H18)-1 -> 0.2519 | I22: =(1+I14)*(1+I18)-1 -> 0.1058 | J22: =(1+J14)*(1+J18)-1 -> 0.0602 | K22: =(1+K14)*(1+K18)-1 -> 0.0602
C23: NAND | G23: =(1+G15)*(1+G19)-1 -> 0.2882 | H23: =(1+H15)*(1+H19)-1 -> 0.1856 | I23: =(1+I15)*(1+I19)-1 -> 0.0944 | J23: =(1+J15)*(1+J19)-1 -> 0.0528 | K23: =(1+K15)*(1+K19)-1 -> 0.0434

Sheet Sheet3
